insipher/__init__.py
insipher/algorithm.py
insipher/error.py
insipher-1.1.5.dist-info/LICENSE
insipher-1.1.5.dist-info/METADATA
insipher-1.1.5.dist-info/WHEEL
insipher-1.1.5.dist-info/top_level.txt
insipher-1.1.5.dist-info/RECORD
