Metadata-Version: 2.1
Name: insipher
Version: 1.1.5
Summary: Insipher Python SDK
Home-page: https://www.insipher.com
Author: Insipher
Author-email: info@insipher.com
License: MIT
Platform: UNKNOWN
License-File: LICENSE
Requires-Dist: uvicorn (==0.13.4)
Requires-Dist: fastapi (==0.63.0)
Requires-Dist: minio (==7.0.2)
Requires-Dist: pyyaml (==5.4.1)
